helpers.py
pbs.py
pbsexceptions.py
pybossa_pbs-2.4.7.dist-info/DESCRIPTION.rst
pybossa_pbs-2.4.7.dist-info/METADATA
pybossa_pbs-2.4.7.dist-info/RECORD
pybossa_pbs-2.4.7.dist-info/WHEEL
pybossa_pbs-2.4.7.dist-info/entry_points.txt
pybossa_pbs-2.4.7.dist-info/metadata.json
pybossa_pbs-2.4.7.dist-info/top_level.txt
