Metadata-Version: 2.0
Name: pybossa-pbs
Version: 2.4.7
Summary: PYBOSSA command line client
Home-page: https://github.com/Scifabric/pbs
Author: Scifabric LTD
Author-email: info@scifabric.com
License: AGPLv3
Platform: UNKNOWN
Classifier: Development Status :: 4 - Beta
Classifier: Environment :: Console
Classifier: Intended Audience :: Developers
Classifier: License :: OSI Approved :: GNU Affero General Public License v3 or later (AGPLv3+)
Classifier: Operating System :: OS Independent
Classifier: Programming Language :: Python
Requires-Dist: Click (<2.4,>=2.3)
Requires-Dist: pybossa-client (<1.2.2,>=1.2.1)
Requires-Dist: requests
Requires-Dist: nose
Requires-Dist: mock
Requires-Dist: coverage
Requires-Dist: rednose
Requires-Dist: pypandoc
Requires-Dist: simplejson
Requires-Dist: jsonschema
Requires-Dist: polib
Requires-Dist: watchdog
Requires-Dist: openpyxl
